enumageddon/__init__.py
enumageddon/main.py
enumageddon/__pycache__/__init__.cpython-310.pyc
enumageddon/__pycache__/main.cpython-310.pyc
enumageddon-1.0.4.dist-info/licenses/LICENSE
enumageddon-1.0.4.dist-info/METADATA
enumageddon-1.0.4.dist-info/WHEEL
enumageddon-1.0.4.dist-info/entry_points.txt
enumageddon-1.0.4.dist-info/top_level.txt
enumageddon-1.0.4.dist-info/RECORD
