Metadata-Version: 2.4
Name: enumageddon
Version: 1.0.4
Summary: A powerful multi-threaded web fuzzer and OSINT tool for discovering endpoints and cloud services
Home-page: https://github.com/yourusername/enumageddon
Author: Not-4O4
Author-email: Not-4O4 <security@example.com>
License: MIT
Project-URL: Homepage, https://github.com/yourusername/enumageddon
Project-URL: Bug Tracker, https://github.com/yourusername/enumageddon/issues
Project-URL: Documentation, https://github.com/yourusername/enumageddon#readme
Project-URL: Source Code, https://github.com/yourusername/enumageddon
Keywords: fuzzing,enumeration,osint,security,bug-bounty,cloud,aws,gcp,azure,web-testing
Classifier: Programming Language :: Python :: 3
Classifier: Programming Language :: Python :: 3.7
Classifier: Programming Language :: Python :: 3.8
Classifier: Programming Language :: Python :: 3.9
Classifier: Programming Language :: Python :: 3.10
Classifier: Programming Language :: Python :: 3.11
Classifier: License :: OSI Approved :: MIT License
Classifier: Operating System :: OS Independent
Classifier: Environment :: Console
Classifier: Topic :: Internet :: WWW/HTTP
Classifier: Topic :: Security
Classifier: Intended Audience :: Information Technology
Classifier: Intended Audience :: System Administrators
Requires-Python: >=3.7
License-File: LICENSE
Requires-Dist: requests>=2.31.0
Requires-Dist: dnspython>=2.4.0
Requires-Dist: python-dotenv>=1.0.0
Provides-Extra: dev
Requires-Dist: pytest>=7.0; extra == "dev"
Requires-Dist: black>=22.0; extra == "dev"
Requires-Dist: flake8>=4.0; extra == "dev"
Dynamic: author
Dynamic: home-page
Dynamic: license-file
Dynamic: requires-python
